Workbook

Sheet CAPA
B60: Planilha: Resumo
B65: Planilha: Títular
B70: Planilha: Informes
B76: Planilha: Notas
B82: IMPORTANTE!

Sheet RESUMO
C4: RESUMO GERAL IMPOSTO DE RENDA
C5: Visão rápida total entradas, origem das entradas e valor estimado dos imposto.
C7: NOME | D7: =TITULAR!D7 -> NNNNNNNNNN NNNNNNNN
C8: CPF | D8: =TITULAR!D8 -> 000.000.000-3
C9: ENDEREÇO RESIDENTE | D9: =TITULAR!D12 -> R. NOMERUA, Nº 000 - CIDADE - ESTADO
C11: TOTAL DE ENTRADAS | D11: =NOTAS!D9 -> 517496
C12: VALOR ESTIMADO DOS IMPOSTOS | D12: =NOTAS!E9 -> 92517.27

Sheet TITULAR
C4: DADOS DO TÍTULAR
C5: Preencha com os dados da pessoa física
C7: NOME | D7: NNNNNNNNNN NNNNNNNN
C8: CPF | D8: 000.000.000-3
C9: NASCIMENTO | D9: 00/00/00
C10: Nº TITULO DE ELEITOR | D10: 222222222
C11: CÔNJUGUE | D11: NNNNNNNNNN NNNNNNNN
C12: ENDEREÇO RESIDENTE | D12: R. NOMERUA, Nº 000 - CIDADE - ESTADO
C13: CEP | D13: 00000-00
C14: TELEFONE | D14: (00) 0000-0000
C15: CELULAR | D15: (00) 0 0000-0000
C16: E-MAIL | D16: XXXXX@EMAIL.COM
C17: HOUVE ALTERAÇÕES DA ENTREGA ANTERIOR? | D17: NÃO
C18: DEPENDENTE CÔNJUGUE | D18: SIM
C19: RESIDENTE NO EXTERIOR? | D19: SIM

Sheet INFORME
C4: INFORMES DE RENDIMENTO BANCÁRIO
C5: Ranking dos bancos com maior histórico de entradas. Anexe o extrato em (.pdf) para comparação.
C7: TOTAL
C8: =SUM(NOTAS!F13:F53) -> 517496
C10: BANCOS MAIS UTILIZADOS
C12: 1 º Banco
C13: BANCO | D13: =IF( MAX(TABELAS!$B$3:$B$21)=0,"-", INDEX(TABELAS!$A$3:$A$21,MATCH(MAX(TABELAS!$B$3:$B$21),TABELAS!$B$3:$B$21,0))) -> 11 - BANCO D
C14: VALOR ANUAL | D14: =SUMIF(Tabela24[[BANCO]:[VALOR]],INFORME!D13,Tabela24[VALOR]) -> 67512
C15: ANEXO | D15: ANEXO_BANCOXYZ_.pdf
C17: 2º Banco
C18: BANCO | D18: =IF(LARGE(TABELAS!$B$3:$B$21,2)=0,"-", INDEX(TABELAS!$A$3:$A$21, MATCH(LARGE(TABELAS!$B$3:$B$21,2),TABELAS!$B$3:$B$21,0))) -> 283 - BANCO G
C19: VALOR ANUAL | D19: =SUMIF(Tabela24[[BANCO]:[VALOR]],INFORME!D18,Tabela24[VALOR]) -> 51670
C20: ANEXO | D20: ANEXO_BANCOXYZ_.pdf
C22: 3º Banco
C23: BANCO | D23: =IF( LARGE(TABELAS!$B$3:$B$21,3)=0,"-", INDEX(TABELAS!$A$3:$A$21, MATCH(LARGE(TABELAS!$B$3:$B$21,3),TABELAS!$B$3:$B$21,0))) -> 202 - BANCO B
C24: VALOR ANUAL | D24: =SUMIF(Tabela24[[BANCO]:[VALOR]],INFORME!D23,Tabela24[VALOR]) -> 61962
C25: ANEXO | D25: ANEXO_BANCOXYZ_.pdf

Sheet NOTAS
C4: NOTAS FISCAIS
C5: Preencha com valores nas celulas em amarelo, escolha a partir de uma lista nas celulas em laranja.
D7: TOTAL DE ENTRADAS | E7: TOTAL DE IMPOSTOS | F7: TOTAL POR ORIGEM | G7: TOTAL POR BANCO
F8: ALUGUEL | G8: 11 - BANCO D
D9: =SUM(Tabela24[VALOR]) -> 517496 | E9: =SUM(Tabela24[Valor Estimado Imposto]) -> 92517.27 | F9: =SUMIF(Tabela24[[ORIGEM]:[VALOR]],F8,Tabela24[VALOR]) -> 151905 | G9: =SUMIF(Tabela24[[BANCO]:[VALOR]],G8,Tabela24[VALOR]) -> 67512
C11: ENTRADAS
C12: DATA | D12: ORIGEM | E12: BANCO | F12: VALOR | G12: Valor Estimado Imposto
C13: 46340 | D13: PRESTAÇÃO DE SERVIÇO | E13: 202 - BANCO B | F13: 19051 | G13: =IF(Tabela24[[#This Row],[ORIGEM]] = TABELAS!$E$3,(Tabela24[[#This Row],[VALOR]]*TABELAS!$F$3/100)*100, IF(Tabela24[[#This Row],[ORIGEM]] = TABELAS!$E$4,(Tabela24[[#This Row],[VALOR]]*TABELAS!$F$4/100)*100, IF(Tabela24[[#This Row],[ORIGEM]] = TABELAS!$E$5,(Tabela24[[#This Row],[VALOR]]*TABELAS!$F$5/100)*100, IF(Tabela24[[#This Row],[ORIGEM]] = TABELAS!$E$6,(Tabela24[[#This Row],[VALOR]]*TABELAS!$F$6/100)*100, IF(Tabela24[[#This Row],[ORIGEM]] = TABELAS!$E$7,(Tabela24[[#This Row],[VALOR]]*TABELAS!$F$7/100)*100, ))))) -> 2667.14
C14: 48752 | D14: ALUGUEL | E14: 202 - BANCO B | F14: 19866 | G14: =IF(Tabela24[[#This Row],[ORIGEM]] = TABELAS!$E$3,(Tabela24[[#This Row],[VALOR]]*TABELAS!$F$3/100)*100, IF(Tabela24[[#This Row],[ORIGEM]] = TABELAS!$E$4,(Tabela24[[#This Row],[VALOR]]*TABELAS!$F$4/100)*100, IF(Tabela24[[#This Row],[ORIGEM]] = TABELAS!$E$5,(Tabela24[[#This Row],[VALOR]]*TABELAS!$F$5/100)*100, IF(Tabela24[[#This Row],[ORIGEM]] = TABELAS!$E$6,(Tabela24[[#This Row],[VALOR]]*TABELAS!$F$6/100)*100, IF(Tabela24[[#This Row],[ORIGEM]] = TABELAS!$E$7,(Tabela24[[#This Row],[VALOR]]*TABELAS!$F$7/100)*100, ))))) -> 4569.18
C15: 45906 | D15: PRESTAÇÃO DE SERVIÇO | E15: 19 - BANCO A | F15: 5633 | G15: =IF(Tabela24[[#This Row],[ORIGEM]] = TABELAS!$E$3,(Tabela24[[#This Row],[VALOR]]*TABELAS!$F$3/100)*100, IF(Tabela24[[#This Row],[ORIGEM]] = TABELAS!$E$4,(Tabela24[[#This Row],[VALOR]]*TABELAS!$F$4/100)*100, IF(Tabela24[[#This Row],[ORIGEM]] = TABELAS!$E$5,(Tabela24[[#This Row],[VALOR]]*TABELAS!$F$5/100)*100, IF(Tabela24[[#This Row],[ORIGEM]] = TABELAS!$E$6,(Tabela24[[#This Row],[VALOR]]*TABELAS!$F$6/100)*100, IF(Tabela24[[#This Row],[ORIGEM]] = TABELAS!$E$7,(Tabela24[[#This Row],[VALOR]]*TABELAS!$F$7/100)*100, ))))) -> 788.62
C16: 45373 | D16: RENDA FIXA | E16: 11 - BANCO D | F16: 9780 | G16: =IF(Tabela24[[#This Row],[ORIGEM]] = TABELAS!$E$3,(Tabela24[[#This Row],[VALOR]]*TABELAS!$F$3/100)*100, IF(Tabela24[[#This Row],[ORIGEM]] = TABELAS!$E$4,(Tabela24[[#This Row],[VALOR]]*TABELAS!$F$4/100)*100, IF(Tabela24[[#This Row],[ORIGEM]] = TABELAS!$E$5,(Tabela24[[#This Row],[VALOR]]*TABELAS!$F$5/100)*100, IF(Tabela24[[#This Row],[ORIGEM]] = TABELAS!$E$6,(Tabela24[[#This Row],[VALOR]]*TABELAS!$F$6/100)*100, IF(Tabela24[[#This Row],[ORIGEM]] = TABELAS!$E$7,(Tabela24[[#This Row],[VALOR]]*TABELAS!$F$7/100)*100, ))))) -> 1956
C17: 46492 | D17: ALUGUEL | E17: 256 - BANCO F | F17: 18154 | G17: =IF(Tabela24[[#This Row],[ORIGEM]] = TABELAS!$E$3,(Tabela24[[#This Row],[VALOR]]*TABELAS!$F$3/100)*100, IF(Tabela24[[#This Row],[ORIGEM]] = TABELAS!$E$4,(Tabela24[[#This Row],[VALOR]]*TABELAS!$F$4/100)*100, IF(Tabela24[[#This Row],[ORIGEM]] = TABELAS!$E$5,(Tabela24[[#This Row],[VALOR]]*TABELAS!$F$5/100)*100, IF(Tabela24[[#This Row],[ORIGEM]] = TABELAS!$E$6,(Tabela24[[#This Row],[VALOR]]*TABELAS!$F$6/100)*100, IF(Tabela24[[#This Row],[ORIGEM]] = TABELAS!$E$7,(Tabela24[[#This Row],[VALOR]]*TABELAS!$F$7/100)*100, ))))) -> 4175.42
C18: 49323 | D18: RENDA FIXA | E18: 261 - BANCO E | F18: 16626 | G18: =IF(Tabela24[[#This Row],[ORIGEM]] = TABELAS!$E$3,(Tabela24[[#This Row],[VALOR]]*TABELAS!$F$3/100)*100, IF(Tabela24[[#This Row],[ORIGEM]] = TABELAS!$E$4,(Tabela24[[#This Row],[VALOR]]*TABELAS!$F$4/100)*100, IF(Tabela24[[#This Row],[ORIGEM]] = TABELAS!$E$5,(Tabela24[[#This Row],[VALOR]]*TABELAS!$F$5/100)*100, IF(Tabela24[[#This Row],[ORIGEM]] = TABELAS!$E$6,(Tabela24[[#This Row],[VALOR]]*TABELAS!$F$6/100)*100, IF(Tabela24[[#This Row],[ORIGEM]] = TABELAS!$E$7,(Tabela24[[#This Row],[VALOR]]*TABELAS!$F$7/100)*100, ))))) -> 3325.2
C19: 49193 | D19: SALÁRIO | E19: 11 - BANCO D | F19: 9204 | G19: =IF(Tabela24[[#This Row],[ORIGEM]] = TABELAS!$E$3,(Tabela24[[#This Row],[VALOR]]*TABELAS!$F$3/100)*100, IF(Tabela24[[#This Row],[ORIGEM]] = TABELAS!$E$4,(Tabela24[[#This Row],[VALOR]]*TABELAS!$F$4/100)*100, IF(Tabela24[[#This Row],[ORIGEM]] = TABELAS!$E$5,(Tabela24[[#This Row],[VALOR]]*TABELAS!$F$5/100)*100, IF(Tabela24[[#This Row],[ORIGEM]] = TABELAS!$E$6,(Tabela24[[#This Row],[VALOR]]*TABELAS!$F$6/100)*100, IF(Tabela24[[#This Row],[ORIGEM]] = TABELAS!$E$7,(Tabela24[[#This Row],[VALOR]]*TABELAS!$F$7/100)*100, ))))) -> 736.32
C20: 46531 | D20: PRESTAÇÃO DE SERVIÇO | E20: 164 - BANCO C | F20: 9937 | G20: =IF(Tabela24[[#This Row],[ORIGEM]] = TABELAS!$E$3,(Tabela24[[#This Row],[VALOR]]*TABELAS!$F$3/100)*100, IF(Tabela24[[#This Row],[ORIGEM]] = TABELAS!$E$4,(Tabela24[[#This Row],[VALOR]]*TABELAS!$F$4/100)*100, IF(Tabela24[[#This Row],[ORIGEM]] = TABELAS!$E$5,(Tabela24[[#This Row],[VALOR]]*TABELAS!$F$5/100)*100, IF(Tabela24[[#This Row],[ORIGEM]] = TABELAS!$E$6,(Tabela24[[#This Row],[VALOR]]*TABELAS!$F$6/100)*100, IF(Tabela24[[#This Row],[ORIGEM]] = TABELAS!$E$7,(Tabela24[[#This Row],[VALOR]]*TABELAS!$F$7/100)*100, ))))) -> 1391.18
C21: 47861 | D21: ALUGUEL | E21: 124 - BANCO P | F21: 7795 | G21: =IF(Tabela24[[#This Row],[ORIGEM]] = TABELAS!$E$3,(Tabela24[[#This Row],[VALOR]]*TABELAS!$F$3/100)*100, IF(Tabela24[[#This Row],[ORIGEM]] = TABELAS!$E$4,(Tabela24[[#This Row],[VALOR]]*TABELAS!$F$4/100)*100, IF(Tabela24[[#This Row],[ORIGEM]] = TABELAS!$E$5,(Tabela24[[#This Row],[VALOR]]*TABELAS!$F$5/100)*100, IF(Tabela24[[#This Row],[ORIGEM]] = TABELAS!$E$6,(Tabela24[[#This Row],[VALOR]]*TABELAS!$F$6/100)*100, IF(Tabela24[[#This Row],[ORIGEM]] = TABELAS!$E$7,(Tabela24[[#This Row],[VALOR]]*TABELAS!$F$7/100)*100, ))))) -> 1792.85
C22: 46721 | D22: ALUGUEL | E22: 283 - BANCO G | F22: 11915 | G22: =IF(Tabela24[[#This Row],[ORIGEM]] = TABELAS!$E$3,(Tabela24[[#This Row],[VALOR]]*TABELAS!$F$3/100)*100, IF(Tabela24[[#This Row],[ORIGEM]] = TABELAS!$E$4,(Tabela24[[#This Row],[VALOR]]*TABELAS!$F$4/100)*100, IF(Tabela24[[#This Row],[ORIGEM]] = TABELAS!$E$5,(Tabela24[[#This Row],[VALOR]]*TABELAS!$F$5/100)*100, IF(Tabela24[[#This Row],[ORIGEM]] = TABELAS!$E$6,(Tabela24[[#This Row],[VALOR]]*TABELAS!$F$6/100)*100, IF(Tabela24[[#This Row],[ORIGEM]] = TABELAS!$E$7,(Tabela24[[#This Row],[VALOR]]*TABELAS!$F$7/100)*100, ))))) -> 2740.45
C23: 47572 | D23: RENDA FIXA | E23: 11 - BANCO D | F23: 14029 | G23: =IF(Tabela24[[#This Row],[ORIGEM]] = TABELAS!$E$3,(Tabela24[[#This Row],[VALOR]]*TABELAS!$F$3/100)*100, IF(Tabela24[[#This Row],[ORIGEM]] = TABELAS!$E$4,(Tabela24[[#This Row],[VALOR]]*TABELAS!$F$4/100)*100, IF(Tabela24[[#This Row],[ORIGEM]] = TABELAS!$E$5,(Tabela24[[#This Row],[VALOR]]*TABELAS!$F$5/100)*100, IF(Tabela24[[#This Row],[ORIGEM]] = TABELAS!$E$6,(Tabela24[[#This Row],[VALOR]]*TABELAS!$F$6/100)*100, IF(Tabela24[[#This Row],[ORIGEM]] = TABELAS!$E$7,(Tabela24[[#This Row],[VALOR]]*TABELAS!$F$7/100)*100, ))))) -> 2805.8
C24: 48957 | D24: AÇÕES | E24: 151 - BANCO M | F24: 18315 | G24: =IF(Tabela24[[#This Row],[ORIGEM]] = TABELAS!$E$3,(Tabela24[[#This Row],[VALOR]]*TABELAS!$F$3/100)*100, IF(Tabela24[[#This Row],[ORIGEM]] = TABELAS!$E$4,(Tabela24[[#This Row],[VALOR]]*TABELAS!$F$4/100)*100, IF(Tabela24[[#This Row],[ORIGEM]] = TABELAS!$E$5,(Tabela24[[#This Row],[VALOR]]*TABELAS!$F$5/100)*100, IF(Tabela24[[#This Row],[ORIGEM]] = TABELAS!$E$6,(Tabela24[[#This Row],[VALOR]]*TABELAS!$F$6/100)*100, IF(Tabela24[[#This Row],[ORIGEM]] = TABELAS!$E$7,(Tabela24[[#This Row],[VALOR]]*TABELAS!$F$7/100)*100, ))))) -> 3296.7
... C53: 45545 | D53: SALÁRIO | E53: 256 - BANCO F | F53: 8855 | G53: =IF(Tabela24[[#This Row],[ORIGEM]] = TABELAS!$E$3,(Tabela24[[#This Row],[VALOR]]*TABELAS!$F$3/100)*100, IF(Tabela24[[#This Row],[ORIGEM]] = TABELAS!$E$4,(Tabela24[[#This Row],[VALOR]]*TABELAS!$F$4/100)*100, IF(Tabela24[[#This Row],[ORIGEM]] = TABELAS!$E$5,(Tabela24[[#This Row],[VALOR]]*TABELAS!$F$5/100)*100, IF(Tabela24[[#This Row],[ORIGEM]] = TABELAS!$E$6,(Tabela24[[#This Row],[VALOR]]*TABELAS!$F$6/100)*100, IF(Tabela24[[#This Row],[ORIGEM]] = TABELAS!$E$7,(Tabela24[[#This Row],[VALOR]]*TABELAS!$F$7/100)*100, ))))) -> 708.4

Sheet TABELAS
A2: BANCO | B2: QTD DIGITADAS | C2: DATA ULTIMO REGISTRO | E2: ORIGEM | F2: % IMPOSTO POR ORIGEM | G2: VALOR TOTAL POR ORIGEM | H2: VALOR IMPOSTO POR ORIGEM
A3: 19 - BANCO A | B3: =COUNTIF(Tabela24[BANCO],TABELAS!A3) -> 2 | C3: {=IFERROR(IF(MAX(IF(Tabela24[BANCO]=TABELAS!A3,Tabela24[DATA]))=0,"-",MAX(IF(Tabela24[BANCO]=TABELAS!A3,Tabela24[DATA]))),"-")} -> 49267 | E3: SALÁRIO | F3: 0.08 | G3: =SUMIF(Tabela24[[ORIGEM]:[VALOR]],TABELAS!E3,Tabela24[VALOR]) -> 54993 | H3: =SUMIF(Tabela24[[ORIGEM]:[Valor Estimado Imposto]],TABELAS!E3,Tabela24[Valor Estimado Imposto]) -> 4399.44
A4: 202 - BANCO B | B4: =COUNTIF(Tabela24[BANCO],TABELAS!A4) -> 4 | C4: {=IFERROR(IF(MAX(IF(Tabela24[BANCO]=TABELAS!A4,Tabela24[DATA]))=0,"-",MAX(IF(Tabela24[BANCO]=TABELAS!A4,Tabela24[DATA]))),"-")} -> 48757 | E4: PRESTAÇÃO DE SERVIÇO | F4: 0.14 | G4: =SUMIF(Tabela24[[ORIGEM]:[VALOR]],TABELAS!E4,Tabela24[VALOR]) -> 129276 | H4: =SUMIF(Tabela24[[ORIGEM]:[Valor Estimado Imposto]],TABELAS!E4,Tabela24[Valor Estimado Imposto]) -> 18098.64
A5: 164 - BANCO C | B5: =COUNTIF(Tabela24[BANCO],TABELAS!A5) -> 4 | C5: {=IFERROR(IF(MAX(IF(Tabela24[BANCO]=TABELAS!A5,Tabela24[DATA]))=0,"-",MAX(IF(Tabela24[BANCO]=TABELAS!A5,Tabela24[DATA]))),"-")} -> 46531 | E5: ALUGUEL | F5: 0.23 | G5: =SUMIF(Tabela24[[ORIGEM]:[VALOR]],TABELAS!E5,Tabela24[VALOR]) -> 151905 | H5: =SUMIF(Tabela24[[ORIGEM]:[Valor Estimado Imposto]],TABELAS!E5,Tabela24[Valor Estimado Imposto]) -> 34938.15
A6: 11 - BANCO D | B6: =COUNTIF(Tabela24[BANCO],TABELAS!A6) -> 6 | C6: {=IFERROR(IF(MAX(IF(Tabela24[BANCO]=TABELAS!A6,Tabela24[DATA]))=0,"-",MAX(IF(Tabela24[BANCO]=TABELAS!A6,Tabela24[DATA]))),"-")} -> 49193 | E6: RENDA FIXA | F6: 0.2 | G6: =SUMIF(Tabela24[[ORIGEM]:[VALOR]],TABELAS!E6,Tabela24[VALOR]) -> 122154 | H6: =SUMIF(Tabela24[[ORIGEM]:[Valor Estimado Imposto]],TABELAS!E6,Tabela24[Valor Estimado Imposto]) -> 24430.8
A7: 261 - BANCO E | B7: =COUNTIF(Tabela24[BANCO],TABELAS!A7) -> 2 | C7: {=IFERROR(IF(MAX(IF(Tabela24[BANCO]=TABELAS!A7,Tabela24[DATA]))=0,"-",MAX(IF(Tabela24[BANCO]=TABELAS!A7,Tabela24[DATA]))),"-")} -> 49323 | E7: AÇÕES | F7: 0.18 | G7: =SUMIF(Tabela24[[ORIGEM]:[VALOR]],TABELAS!E7,Tabela24[VALOR]) -> 59168 | H7: =SUMIF(Tabela24[[ORIGEM]:[Valor Estimado Imposto]],TABELAS!E7,Tabela24[Valor Estimado Imposto]) -> 10650.24
A8: 256 - BANCO F | B8: =COUNTIF(Tabela24[BANCO],TABELAS!A8) -> 3 | C8: {=IFERROR(IF(MAX(IF(Tabela24[BANCO]=TABELAS!A8,Tabela24[DATA]))=0,"-",MAX(IF(Tabela24[BANCO]=TABELAS!A8,Tabela24[DATA]))),"-")} -> 49064
A9: 283 - BANCO G | B9: =COUNTIF(Tabela24[BANCO],TABELAS!A9) -> 5 | C9: {=IFERROR(IF(MAX(IF(Tabela24[BANCO]=TABELAS!A9,Tabela24[DATA]))=0,"-",MAX(IF(Tabela24[BANCO]=TABELAS!A9,Tabela24[DATA]))),"-")} -> 49947
A10: 18 - BANCO H | B10: =COUNTIF(Tabela24[BANCO],TABELAS!A10) -> 0 | C10: {=IFERROR(IF(MAX(IF(Tabela24[BANCO]=TABELAS!A10,Tabela24[DATA]))=0,"-",MAX(IF(Tabela24[BANCO]=TABELAS!A10,Tabela24[DATA]))),"-")} -> -
A11: 142 - BANCO I | B11: =COUNTIF(Tabela24[BANCO],TABELAS!A11) -> 1 | C11: {=IFERROR(IF(MAX(IF(Tabela24[BANCO]=TABELAS!A11,Tabela24[DATA]))=0,"-",MAX(IF(Tabela24[BANCO]=TABELAS!A11,Tabela24[DATA]))),"-")} -> 49597
A12: 236 - BANCO J | B12: =COUNTIF(Tabela24[BANCO],TABELAS!A12) -> 2 | C12: {=IFERROR(IF(MAX(IF(Tabela24[BANCO]=TABELAS!A12,Tabela24[DATA]))=0,"-",MAX(IF(Tabela24[BANCO]=TABELAS!A12,Tabela24[DATA]))),"-")} -> 49751
A13: 58 - BANCO K | B13: =COUNTIF(Tabela24[BANCO],TABELAS!A13) -> 1 | C13: {=IFERROR(IF(MAX(IF(Tabela24[BANCO]=TABELAS!A13,Tabela24[DATA]))=0,"-",MAX(IF(Tabela24[BANCO]=TABELAS!A13,Tabela24[DATA]))),"-")} -> 48367
A14: 384 - BANCO L | B14: =COUNTIF(Tabela24[BANCO],TABELAS!A14) -> 1 | C14: {=IFERROR(IF(MAX(IF(Tabela24[BANCO]=TABELAS!A14,Tabela24[DATA]))=0,"-",MAX(IF(Tabela24[BANCO]=TABELAS!A14,Tabela24[DATA]))),"-")} -> 48973
A15: 151 - BANCO M | B15: =COUNTIF(Tabela24[BANCO],TABELAS!A15) -> 3 | C15: {=IFERROR(IF(MAX(IF(Tabela24[BANCO]=TABELAS!A15,Tabela24[DATA]))=0,"-",MAX(IF(Tabela24[BANCO]=TABELAS!A15,Tabela24[DATA]))),"-")} -> 48957
A16: 18 - BANCO N | B16: =COUNTIF(Tabela24[BANCO],TABELAS!A16) -> 1 | C16: {=IFERROR(IF(MAX(IF(Tabela24[BANCO]=TABELAS!A16,Tabela24[DATA]))=0,"-",MAX(IF(Tabela24[BANCO]=TABELAS!A16,Tabela24[DATA]))),"-")} -> 47158
A17: 273 - BANCO O | B17: =COUNTIF(Tabela24[BANCO],TABELAS!A17) -> 1 | C17: {=IFERROR(IF(MAX(IF(Tabela24[BANCO]=TABELAS!A17,Tabela24[DATA]))=0,"-",MAX(IF(Tabela24[BANCO]=TABELAS!A17,Tabela24[DATA]))),"-")} -> 48175
A18: 124 - BANCO P | B18: =COUNTIF(Tabela24[BANCO],TABELAS!A18) -> 2 | C18: {=IFERROR(IF(MAX(IF(Tabela24[BANCO]=TABELAS!A18,Tabela24[DATA]))=0,"-",MAX(IF(Tabela24[BANCO]=TABELAS!A18,Tabela24[DATA]))),"-")} -> 49482
A19: 38 - BANCO Q | B19: =COUNTIF(Tabela24[BANCO],TABELAS!A19) -> 1 | C19: {=IFERROR(IF(MAX(IF(Tabela24[BANCO]=TABELAS!A19,Tabela24[DATA]))=0,"-",MAX(IF(Tabela24[BANCO]=TABELAS!A19,Tabela24[DATA]))),"-")} -> 47741
... A21: 388 - BANCO S | B21: =COUNTIF(Tabela24[BANCO],TABELAS!A21) -> 1 | C21: {=IFERROR(IF(MAX(IF(Tabela24[BANCO]=TABELAS!A21,Tabela24[DATA]))=0,"-",MAX(IF(Tabela24[BANCO]=TABELAS!A21,Tabela24[DATA]))),"-")} -> 47930
